pyligent/__init__.py
pyligent/common/__init__.py
pyligent/common/config.py
pyligent/common/factories.py
pyligent/common/tensorboard_logger.py
pyligent/common/training.py
pyligent/common/utils/__init__.py
pyligent/common/utils/fs.py
pyligent/common/utils/global_config.py
pyligent/common/utils/logger.py
pyligent/common/utils/seed.py
pyligent/common/visualize.py
pyligent/core/__init__.py
pyligent/core/action.py
pyligent/core/dataset.py
pyligent/core/datasets/sampling_strategies.py
pyligent/core/evaluator.py
pyligent/core/explorer.py
pyligent/core/explorers/EXPLORER.md
pyligent/core/explorers/__init__.py
pyligent/core/explorers/dendritic_explorer.py
pyligent/core/explorers/linear_explorer.py
pyligent/core/explorers/sampling_explorer.py
pyligent/core/helpers/__init__.py
pyligent/core/helpers/action_parser.py
pyligent/core/helpers/backtrack_policy.py
pyligent/core/helpers/explore_techniques.py
pyligent/core/helpers/log_manager.py
pyligent/core/helpers/logging_config.py
pyligent/core/helpers/pipeline_components.py
pyligent/core/helpers/training_logger.py
pyligent/core/path.py
pyligent/core/pipeline.py
pyligent/core/solver.py
pyligent/core/solvers/__init__.py
pyligent/core/solvers/guidance.py
pyligent/core/solvers/llm.py
pyligent/core/solvers/llm_helpers.py
pyligent/core/solvers/solver-acc.py
pyligent/core/solvers/solver-new.py
pyligent/core/state.py
pyligent/core/validator.py
pyligent/data/build_golden_paths.py
pyligent/data/build_phase_dataset.py
pyligent/evaluators/gsm8k_evaluator.py
pyligent/scripts/README.md
pyligent/scripts/sudoku/GENERATION.md
pyligent/scripts/sudoku/README.md
pyligent/scripts/sudoku/generation.py
pyligent/tasks/__init__.py
pyligent/tasks/blocksworld/VAL/.cvsignore
pyligent/tasks/blocksworld/VAL/LICENSE
pyligent/tasks/blocksworld/VAL/Make.files
pyligent/tasks/blocksworld/VAL/Make.header
pyligent/tasks/blocksworld/VAL/Makefile
pyligent/tasks/blocksworld/VAL/Papers on Val/aaai05.pdf
pyligent/tasks/blocksworld/VAL/Papers on Val/ictai.pdf
pyligent-0.2.2.dist-info/WHEEL
pyligent-0.2.2.dist-info/METADATA
pyligent-0.2.2.dist-info/RECORD
