Metadata-Version: 2.3
Name: pyligent
Version: 0.2.2
Summary: Diligent framework for python
Keywords: reasoning,llm,transformers,ml
Author: Dmitry Beresnev, Petr Anokhin, Vladimir Makharev, Roman Khalikov
Author-email: Dmitry Beresnev <d.beresnev.work@gmail.com>, Petr Anokhin <anokhin@airi.net>
Classifier: Development Status :: 3 - Alpha
Classifier: Intended Audience :: Developers
Classifier: Intended Audience :: Science/Research
Classifier: Programming Language :: Python :: 3
Classifier: Programming Language :: Python :: 3.13
Classifier: Topic :: Scientific/Engineering :: Artificial Intelligence
Requires-Dist: bitsandbytes>=0.48.1
Requires-Dist: datasets>=4.0.0
Requires-Dist: ipykernel>=6.30.1
Requires-Dist: ipywidgets>=8.1.7
Requires-Dist: loguru>=0.7.3
Requires-Dist: numpy>=2.3.2
Requires-Dist: peft>=0.17.1
Requires-Dist: python-dotenv>=1.1.1
Requires-Dist: tqdm>=4.67.1
Requires-Dist: transformers[torch]>=4.56.0
Requires-Dist: trl>=0.22.2
Requires-Dist: tensorboard>=2.20.0
Requires-Dist: networkx[default]>=3.5
Requires-Dist: nvidia-ml-py>=13.580.82
Requires-Dist: orjson>=3.11.5
Requires-Dist: guidance>=0.3.0
Requires-Dist: accelerate>=1.12.0
Requires-Dist: gpustat>=1.1.1
Requires-Dist: pyarrow>=22.0.0
Requires-Dist: torch>=2.8.0 ; extra == 'cpu'
Requires-Dist: torch>=2.8.0 ; extra == 'cu128'
Requires-Python: >=3.13
Provides-Extra: cpu
Provides-Extra: cu128
